<?xml version="1.0"?>
<data>
    <company>
        <company-name>Altera</company-name>
        <website>http://www.altera.com</website>
    </company>
    <company>
        <company-name>Analog Devices</company-name>
        <website>http://www.analog.com</website>
    </company>
    <company>
        <company-name>Bourns</company-name>
        <website>http://www.bourns.com</website>
    </company>
    <company>
        <company-name>Diodes Inc</company-name>
        <website>http://www.diodes.com</website>
    </company>
    <company>
        <company-name>Freescale</company-name>
        <website>http://www.freescale.com</website>
    </company>
    <company>
        <company-name>Hirose</company-name>
        <website>http://www.hirose.com</website>
    </company>
    <company>
        <company-name>IR</company-name>
        <website>http://www.irf.com</website>
    </company>
    <company>
        <company-name>JAE</company-name>
        <website>http://www.jae.co.jp</website>
    </company>
    <company>
        <company-name>Maxim</company-name>
        <website>http://www.maxim-ic.com</website>
    </company>
    <company>
        <company-name>Micron</company-name>
        <website>http://www.micron.com</website>
    </company>
    <company>
        <company-name>Molex</company-name>
        <website>http://www.molex.com</website>
    </company>
    <company>
        <company-name>NXP</company-name>
        <website>http://www.nxp.com</website>
    </company>
    <company>
        <company-name>ON Semiconductor</company-name>
        <website>http://www.onsemi.com</website>
    </company>
    <company>
        <company-name>TI</company-name>
        <website>http://www.ti.com</website>
    </company>
    <company>
        <company-name>Vishay-Dale</company-name>
        <website>http://www.vishay.com/company/brands/dale</website>
    </company>
    <company>
        <company-name>Vishay-Siliconix</company-name>
        <website>http://www.vishay.com/company/brands/siliconix</website>
    </company>
    <company>
        <company-name>Vishay-Sprague</company-name>
        <website>http://www.vishay.com/company/brands/sprague</website>
    </company>
    <company>
        <company-name>Vishay-Vitramon</company-name>
        <website>http://www.vishay.com/company/brands/vitramon</website>
    </company>
    <company>
        <company-name>Xilinx</company-name>
        <website>http://www.xilinx.com</website>
    </company>
</data>

